pywebinfo/__init__.py
pywebinfo/main.py
pywebinfo-1.0.2.dist-info/LICENSE
pywebinfo-1.0.2.dist-info/METADATA
pywebinfo-1.0.2.dist-info/WHEEL
pywebinfo-1.0.2.dist-info/top_level.txt
pywebinfo-1.0.2.dist-info/RECORD
