Metadata-Version: 2.1
Name: pywebinfo
Version: 1.0.2
Summary: A Python module to simply extract metadata (title, description, image, favicon) of a webpage
Home-page: https://github.com/kaustubhrprabhu/pywebinfo
Author: Kaustubh Prabhu
Keywords: python,webpage,website,metadata
License-File: LICENSE
Requires-Dist: requests
Requires-Dist: beautifulsoup4
